floatedu/Float.py
floatedu/__init__.py
floatedu-0.0.3.dist-info/LICENSE
floatedu-0.0.3.dist-info/METADATA
floatedu-0.0.3.dist-info/WHEEL
floatedu-0.0.3.dist-info/top_level.txt
floatedu-0.0.3.dist-info/RECORD
