Metadata-Version: 2.1
Name: floatedu
Version: 0.0.3
Summary: Educational python module to parse floats and inspect the IEEE754 algorithm's internals.
Home-page: https://gitlab.com/geusebi/float-ieee754-didactic
Author: Giampaolo Eusebi
Author-email: giampaolo.eusebi@gmail.com
License: GNU GPL 3.0
Platform: UNKNOWN
Classifier: Development Status :: 4 - Beta
Classifier: Intended Audience :: Science/Research
Classifier: Intended Audience :: Education
Classifier: License :: OSI Approved
Classifier: License :: OSI Approved :: GNU General Public License v3 (GPLv3)
Classifier: Operating System :: OS Independent
Classifier: Programming Language :: Python :: 3
Classifier: Programming Language :: Python :: 3.6
Classifier: Programming Language :: Python :: 3.7
Classifier: Topic :: Education
Requires-Python: >=3.6
